Metadata-Version: 2.4
Name: adafruit-circuitpython-uc8253
Version: 1.0.2
Summary: CircuitPython `displayio` driver for epaper driven by UC8253 driver IC
Author-email: Adafruit Industries <circuitpython@adafruit.com>
License: MIT
Project-URL: Homepage, https://github.com/adafruit/Adafruit_CircuitPython_UC8253
Keywords: adafruit,blinka,circuitpython,micropython,uc8253,UC8253,epd
Classifier: Intended Audience :: Developers
Classifier: Topic :: Software Development :: Libraries
Classifier: Topic :: Software Development :: Embedded Systems
Classifier: Topic :: System :: Hardware
Classifier: License :: OSI Approved :: MIT License
Classifier: Programming Language :: Python :: 3
License-File: LICENSE
Requires-Dist: Adafruit-Blinka
Provides-Extra: optional
Dynamic: license-file
